cli.py
noiv/__init__.py
noiv/cli.py
noiv/ai/__init__.py
noiv/ai/gemini_client.py
noiv/ai/generator.py
noiv/core/__init__.py
noiv/core/config_manager.py
noiv/core/test_engine.py
noiv/core/test_runner.py
noiv/utils/__init__.py
noiv/utils/file_handler.py
noiv/utils/http_client.py
noiv/utils/http_probe.py
noiv/utils/importers.py
noiv/utils/monitor.py
noiv/utils/plugins.py
noiv/utils/reporting.py
noiv-0.2.8.dist-info/licenses/LICENSE
noiv-0.2.8.dist-info/METADATA
noiv-0.2.8.dist-info/WHEEL
noiv-0.2.8.dist-info/entry_points.txt
noiv-0.2.8.dist-info/top_level.txt
noiv-0.2.8.dist-info/RECORD
